01_game_of_life/adder_1.sv
module adder_1(a, b, c_in, sum, c_out);

  input wire a, b;
  input wire c_in;
  output logic sum;
  output logic c_out;

  logic p,g;
  always_comb begin
    p = a ^ b;
    g = a & b;

    sum = p ^ c_in;
    c_out = g | (p & c_in);
  end

endmodule

hw_4/adder_n.sv
module adder_n(a, b, c_in, sum, c_out);

parameter N = 2;

input  wire [N-1:0] a, b;
input wire c_in;
output logic [N-1:0] sum;
output wire c_out;

wire [N:0] carries;
assign carries[0] = c_in;
assign c_out = carries[N];
generate
    genvar i;
    for(i = 0; i < N; i++) begin : ripple_carry
    adder_1 ADDER (.a(a[i]), .b(b[i]), .c_in(carries[i]), .sum(sum[i]), .c_out(carries[i+1]));
  end
endgenerate

endmodule

01_game_of_life/test_adders.sv
`timescale 1ns / 1ps
`default_nettype none

`define SIMULATION

module test_adders;
  logic a,b;
  logic c_in;
  logic sum;
  logic c_out;


  logic [2:0] a_3, b_3;
  logic c_in_3;
  logic [2:0] sum_3;
  logic c_out_3;

  adder_1 UUT_1(.a(a), .b(b), .c_in(c_in), .sum(sum), .c_out(c_out));
  adder_n #(.N(3)) UUT_3 (.a(a_3), .b(b_3), .c_in(c_in_3), .sum(sum_3), .c_out(c_out_3));

  initial begin
    // Collect waveforms
    $dumpfile("adders.vcd");
    $dumpvars(0, UUT_1);
    $dumpvars(0, UUT_3);
    
    c_in = 0;
    $display("1 bit adder");
    $display("c_in a b | sum c_out");
    for (int i = 0; i < 2; i = i + 1) begin
        a = i;
        for (int j = 0; j < 2; j = j + 1) begin
            b = j;
            #1 $display("%1b %1b %1b | %1b %1b", c_in, a, b, sum, c_out);
        end
    end

    c_in = 1;
    
    for (int i = 0; i < 2; i = i + 1) begin
        a = i;
        for (int j = 0; j < 2; j = j + 1) begin
            b = j;
            #1 $display("%1b %1b %1b | %1b %1b", c_in, a, b, sum, c_out);
        end
    end

    c_in_3 = 0;
    $display("3 bit adder");
    $display("c_in a b | sum c_out");

    for (int i = 0; i < 8; i = i + 1) begin
        a_3 = i[2:0];
        for (int j = 0; j < 8; j = j + 1) begin
            b_3 = j[2:0];
            #1 $display("%1b %3b %3b | %3b %1b", c_in_3, a_3, b_3, sum_3, c_out_3);
        end
    end

    c_in_3 = 1;
    for (int i = 0; i < 8; i = i + 1) begin
        a_3 = i[2:0];
        for (int j = 0; j < 8; j = j + 1) begin
            b_3 = j[2:0];
            #1 $display("%1b %3b %3b | %3b %1b", c_in_3, a_3, b_3, sum_3, c_out_3);
        end
    end



    $finish;      
	end

endmodule

01_game_of_life/adders.vcd
$date
	Thu Oct  7 15:55:27 2021
$end
$version
	Icarus Verilog
$end
$timescale
	1ps
$end
$scope module test_adders $end
$scope module UUT_1 $end
$var wire 1 ! a $end
$var wire 1 " b $end
$var wire 1 # c_in $end
$var reg 1 $ c_out $end
$var reg 1 % g $end
$var reg 1 & p $end
$var reg 1 ' sum $end
$upscope $end
$upscope $end
$scope module test_adders $end
$scope module UUT_3 $end
$var wire 3 ( a [2:0] $end
$var wire 3 ) b [2:0] $end
$var wire 1 * c_in $end
$var wire 3 + sum [2:0] $end
$var wire 4 , carries [3:0] $end
$var wire 1 - c_out $end
$scope begin ripple_carry[0] $end
$scope module ADDER $end
$var wire 1 . a $end
$var wire 1 / b $end
$var wire 1 0 c_in $end
$var reg 1 1 c_out $end
$var reg 1 2 g $end
$var reg 1 3 p $end
$var reg 1 4 sum $end
$upscope $end
$upscope $end
$scope begin ripple_carry[1] $end
$scope module ADDER $end
$var wire 1 5 a $end
$var wire 1 6 b $end
$var wire 1 7 c_in $end
$var reg 1 8 c_out $end
$var reg 1 9 g $end
$var reg 1 : p $end
$var reg 1 ; sum $end
$upscope $end
$upscope $end
$scope begin ripple_carry[2] $end
$scope module ADDER $end
$var wire 1 < a $end
$var wire 1 = b $end
$var wire 1 > c_in $end
$var reg 1 ? c_out $end
$var reg 1 @ g $end
$var reg 1 A p $end
$var reg 1 B sum $end
$upscope $end
$upscope $end
$upscope $end
$upscope $end
$enddefinitions $end
#0
$dumpvars
xB
xA
x@
x?
x>
x=
x<
x;
x:
x9
x8
x7
x6
x5
x4
x3
x2
x1
x0
x/
x.
x-
bx ,
bx +
x*
bx )
bx (
0'
0&
0%
0$
0#
0"
0!
$end
#1000
1'
1&
1"
#2000
0"
1!
#3000
1$
0'
1%
0&
1"
#4000
0$
1'
0%
0"
0!
1#
#5000
1$
0'
1&
1"
#6000
0"
1!
#7000
1'
1%
0&
1"
#8000
0B
0;
0>
0-
07
08
09
0:
0?
0@
0A
01
b0 +
04
02
03
0/
06
0=
0.
05
0<
00
b0 )
b0 (
b0 ,
0*
#9000
b1 +
14
13
1/
b1 )
#10000
04
03
b10 +
1;
1:
0/
16
b10 )
#11000
b11 +
14
13
1/
b11 )
#12000
04
03
0;
0:
b100 +
1B
1A
0/
06
1=
b100 )
#13000
b101 +
14
13
1/
b101 )
#14000
04
03
b110 +
1;
1:
0/
16
b110 )
#15000
b111 +
14
13
1/
b111 )
#16000
0;
0:
b1 +
0B
0A
0/
06
0=
1.
b0 )
b1 (
#17000
1;
17
b10 ,
11
b10 +
04
12
03
1/
b1 )
#18000
0B
07
0>
01
14
02
13
b0 ,
08
b11 +
1;
1:
0/
16
b10 )
#19000
1B
1>
18
0;
17
b110 ,
11
b100 +
04
12
03
1/
b11 )
#20000
07
0>
0-
01
14
02
13
08
0;
0:
b0 ,
0?
b101 +
1B
1A
0/
06
1=
b100 )
#21000
1;
17
b10 ,
11
b110 +
04
12
03
1/
b101 )
#22000
0-
0?
1B
07
0>
01
14
02
13
b0 ,
08
b111 +
1;
1:
0/
16
b110 )
#23000
1-
1?
0B
1>
18
0;
17
b1110 ,
11
b0 +
04
12
03
1/
b111 )
#24000
0>
08
1;
0-
07
0?
b10 +
0B
0A
b0 ,
01
02
0/
06
0=
0.
15
b0 )
b10 (
#25000
b11 +
14
13
1/
b1 )
#26000
1B
1>
04
03
b100 ,
18
b100 +
0;
19
0:
0/
16
b10 )
#27000
b101 +
14
13
1/
b11 )
#28000
0>
0-
04
03
08
1;
09
1:
b0 ,
0?
b110 +
1B
1A
0/
06
1=
b100 )
#29000
b111 +
14
13
1/
b101 )
#30000
1-
1?
0B
1>
04
03
b1100 ,
18
b0 +
0;
19
0:
0/
16
b110 )
#31000
b1 +
14
13
1/
b111 )
#32000
0>
0-
08
1;
09
1:
b0 ,
0?
b11 +
0B
0A
0/
06
0=
1.
b0 )
b11 (
#33000
1B
1>
18
0;
17
b110 ,
11
b100 +
04
12
03
1/
b1 )
#34000
07
b100 ,
01
14
02
13
b101 +
0;
19
0:
0/
16
b10 )
#35000
1;
17
b110 ,
11
b110 +
04
12
03
1/
b11 )
#36000
0>
08
07
0-
01
14
02
13
1;
09
1:
b0 ,
0?
b111 +
1B
1A
0/
06
1=
b100 )
#37000
1-
1?
0B
1>
18
0;
17
b1110 ,
11
b0 +
04
12
03
1/
b101 )
#38000
07
b1100 ,
01
14
02
13
b1 +
0;
19
0:
0/
16
b110 )
#39000
1;
17
b1110 ,
11
b10 +
04
12
03
1/
b111 )
#40000
0-
0;
0?
b100 +
1B
07
0>
01
02
b0 ,
08
09
0/
06
0=
0.
05
1<
b0 )
b100 (
#41000
b101 +
14
13
1/
b1 )
#42000
04
03
b110 +
1;
1:
0/
16
b10 )
#43000
b111 +
14
13
1/
b11 )
#44000
1-
04
03
0;
0:
b1000 ,
1?
b0 +
0B
1@
0A
0/
06
1=
b100 )
#45000
b1 +
14
13
1/
b101 )
#46000
04
03
b10 +
1;
1:
0/
16
b110 )
#47000
b11 +
14
13
1/
b111 )
#48000
0-
0;
0:
b0 ,
0?
b101 +
1B
0@
1A
0/
06
0=
1.
b0 )
b101 (
#49000
1;
17
b10 ,
11
b110 +
04
12
03
1/
b1 )
#50000
0-
0?
1B
07
0>
01
14
02
13
b0 ,
08
b111 +
1;
1:
0/
16
b10 )
#51000
1-
1?
0B
1>
18
0;
17
b1110 ,
11
b0 +
04
12
03
1/
b11 )
#52000
07
0>
01
14
02
13
b1000 ,
08
0;
0:
b1 +
0B
1@
0A
0/
06
1=
b100 )
#53000
1;
17
b1010 ,
11
b10 +
04
12
03
1/
b101 )
#54000
0B
07
0>
01
14
02
13
b1000 ,
08
b11 +
1;
1:
0/
16
b110 )
#55000
1B
1>
18
0;
17
b1110 ,
11
b100 +
04
12
03
1/
b111 )
#56000
0-
0?
0>
08
1;
07
b110 +
1B
0@
1A
b0 ,
01
02
0/
06
0=
0.
15
b0 )
b110 (
#57000
b111 +
14
13
1/
b1 )
#58000
1-
1?
0B
1>
04
03
b1100 ,
18
b0 +
0;
19
0:
0/
16
b10 )
#59000
b1 +
14
13
1/
b11 )
#60000
0>
04
03
b1000 ,
08
1;
09
1:
b10 +
0B
1@
0A
0/
06
1=
b100 )
#61000
b11 +
14
13
1/
b101 )
#62000
1B
1>
04
03
b1100 ,
18
b100 +
0;
19
0:
0/
16
b110 )
#63000
b101 +
14
13
1/
b111 )
#64000
0-
0?
0>
b0 ,
08
1;
09
1:
b111 +
1B
0@
1A
0/
06
0=
1.
b0 )
b111 (
#65000
1-
1?
0B
1>
18
0;
17
b1110 ,
11
b0 +
04
12
03
1/
b1 )
#66000
07
b1100 ,
01
14
02
13
b1 +
0;
19
0:
0/
16
b10 )
#67000
1;
17
b1110 ,
11
b10 +
04
12
03
1/
b11 )
#68000
0>
08
07
b1000 ,
01
14
02
13
1;
09
1:
b11 +
0B
1@
0A
0/
06
1=
b100 )
#69000
1B
1>
18
0;
17
b1110 ,
11
b100 +
04
12
03
1/
b101 )
#70000
07
b1100 ,
01
14
02
13
b101 +
0;
19
0:
0/
16
b110 )
#71000
1;
17
b1110 ,
11
b110 +
04
12
03
1/
b111 )
#72000
0B
0;
0>
0-
07
08
09
0?
0@
01
b1 +
14
02
0/
06
0=
0.
05
0<
10
b0 )
b0 (
b1 ,
1*
#73000
1;
17
b11 ,
11
b10 +
04
13
1/
b1 )
#74000
0B
07
0>
01
14
03
b1 ,
08
b11 +
1;
1:
0/
16
b10 )
#75000
1B
1>
18
0;
17
b111 ,
11
b100 +
04
13
1/
b11 )
#76000
07
0>
0-
01
14
03
08
0;
0:
b1 ,
0?
b101 +
1B
1A
0/
06
1=
b100 )
#77000
1;
17
b11 ,
11
b110 +
04
13
1/
b101 )
#78000
0-
0?
1B
07
0>
01
14
03
b1 ,
08
b111 +
1;
1:
0/
16
b110 )
#79000
1-
1?
0B
1>
18
0;
17
b1111 ,
11
b0 +
04
13
1/
b111 )
#80000
0>
0-
08
1;
0:
b11 ,
0?
b10 +
0B
0A
0/
06
0=
1.
b0 )
b1 (
#81000
b11 +
14
12
03
1/
b1 )
#82000
1B
1>
04
02
13
b111 ,
18
b100 +
0;
1:
0/
16
b10 )
#83000
b101 +
14
12
03
1/
b11 )
#84000
0>
0-
04
02
13
08
1;
0:
b11 ,
0?
b110 +
1B
1A
0/
06
1=
b100 )
#85000
b111 +
14
12
03
1/
b101 )
#86000
1-
1?
0B
1>
04
02
13
b1111 ,
18
b0 +
0;
1:
0/
16
b110 )
#87000
b1 +
14
12
03
1/
b111 )
#88000
0>
08
1;
0-
07
0?
b11 +
0B
0A
b1 ,
01
02
0/
06
0=
0.
15
b0 )
b10 (
#89000
1B
1>
18
0;
17
b111 ,
11
b100 +
04
13
1/
b1 )
#90000
07
b101 ,
01
14
03
b101 +
0;
19
0:
0/
16
b10 )
#91000
1;
17
b111 ,
11
b110 +
04
13
1/
b11 )
#92000
0>
08
07
0-
01
14
03
1;
09
1:
b1 ,
0?
b111 +
1B
1A
0/
06
1=
b100 )
#93000
1-
1?
0B
1>
18
0;
17
b1111 ,
11
b0 +
04
13
1/
b101 )
#94000
07
b1101 ,
01
14
03
b1 +
0;
19
0:
0/
16
b110 )
#95000
1;
17
b1111 ,
11
b10 +
04
13
1/
b111 )
#96000
0-
0;
09
1:
b111 ,
0?
b100 +
1B
0A
0/
06
0=
1.
b0 )
b11 (
#97000
b101 +
14
12
03
1/
b1 )
#98000
04
02
13
b110 +
1;
19
0:
0/
16
b10 )
#99000
b111 +
14
12
03
1/
b11 )
#100000
1-
04
02
13
0;
09
1:
b1111 ,
1?
b0 +
0B
1A
0/
06
1=
b100 )
#101000
b1 +
14
12
03
1/
b101 )
#102000
04
02
13
b10 +
1;
19
0:
0/
16
b110 )
#103000
b11 +
14
12
03
1/
b111 )
#104000
0-
0;
0?
b101 +
1B
07
0>
01
02
b1 ,
08
09
0/
06
0=
0.
05
1<
b0 )
b100 (
#105000
1;
17
b11 ,
11
b110 +
04
13
1/
b1 )
#106000
0-
0?
1B
07
0>
01
14
03
b1 ,
08
b111 +
1;
1:
0/
16
b10 )
#107000
1-
1?
0B
1>
18
0;
17
b1111 ,
11
b0 +
04
13
1/
b11 )
#108000
07
0>
01
14
03
b1001 ,
08
0;
0:
b1 +
0B
1@
0A
0/
06
1=
b100 )
#109000
1;
17
b1011 ,
11
b10 +
04
13
1/
b101 )
#110000
0B
07
0>
01
14
03
b1001 ,
08
b11 +
1;
1:
0/
16
b110 )
#111000
1B
1>
18
0;
17
b1111 ,
11
b100 +
04
13
1/
b111 )
#112000
0-
0?
0>
b11 ,
08
1;
0:
b110 +
1B
0@
1A
0/
06
0=
1.
b0 )
b101 (
#113000
b111 +
14
12
03
1/
b1 )
#114000
1-
1?
0B
1>
04
02
13
b1111 ,
18
b0 +
0;
1:
0/
16
b10 )
#115000
b1 +
14
12
03
1/
b11 )
#116000
0>
04
02
13
b1011 ,
08
1;
0:
b10 +
0B
1@
0A
0/
06
1=
b100 )
#117000
b11 +
14
12
03
1/
b101 )
#118000
1B
1>
04
02
13
b1111 ,
18
b100 +
0;
1:
0/
16
b110 )
#119000
b101 +
14
12
03
1/
b111 )
#120000
0-
0?
0>
08
1;
07
b111 +
1B
0@
1A
b1 ,
01
02
0/
06
0=
0.
15
b0 )
b110 (
#121000
1-
1?
0B
1>
18
0;
17
b1111 ,
11
b0 +
04
13
1/
b1 )
#122000
07
b1101 ,
01
14
03
b1 +
0;
19
0:
0/
16
b10 )
#123000
1;
17
b1111 ,
11
b10 +
04
13
1/
b11 )
#124000
0>
08
07
b1001 ,
01
14
03
1;
09
1:
b11 +
0B
1@
0A
0/
06
1=
b100 )
#125000
1B
1>
18
0;
17
b1111 ,
11
b100 +
04
13
1/
b101 )
#126000
07
b1101 ,
01
14
03
b101 +
0;
19
0:
0/
16
b110 )
#127000
1;
17
b1111 ,
11
b110 +
04
13
1/
b111 )
#128000
0;
09
1:
b0 +
0B
0@
1A
0/
06
0=
1.
b0 )
b111 (
#129000
b1 +
14
12
03
1/
b1 )
#130000
04
02
13
b10 +
1;
19
0:
0/
16
b10 )
#131000
b11 +
14
12
03
1/
b11 )
#132000
04
02
13
0;
09
1:
b100 +
1B
1@
0A
0/
06
1=
b100 )
#133000
b101 +
14
12
03
1/
b101 )
#134000
04
02
13
b110 +
1;
19
0:
0/
16
b110 )
#135000
b111 +
14
12
03
1/
b111 )
